{"sections":{"collection-banner":{"type":"collection-banner","disabled":true,"settings":{"show_collection_image":false,"show_collection_description":true,"section_height":"auto","text_width":"large","image_text_color":"#ffffff","image_overlay_color":"#000000","image_overlay_opacity":47,"quick_links":""}},"1655212869259e08a7":{"type":"image-with-text-overlay","settings":{"reveal_on_scroll":false,"loading":"lazy","section_height":"auto","image":"shopify:\/\/shop_images\/panels-header-2000x400_2000x_8f807f80-1846-42e4-818d-a28727d53d2c.webp","subheading":"LED LIGHTING","title":"Lower Your Energy Costs for Less","content":"<p>No need to wait for a sale: Grab a discount code when you sign up for ELEDLights texts, then use it to save on your next LED lighting upgrade or install.<\/p>","button_text":"","button_link":"","link_style":"link","background_type":"full_width","text_width":"medium","text_position":"middle_left","text_color":"#0d0d0d","button_background":"#ffffff","button_text_color":"#000000","overlay_color":"#000000","overlay_opacity":0}},"165540493133ea9de2":{"type":"custom-html","settings":{"subheading":"","title":"","html":"<div style=\"text-align: center\"><a class=\"klaviyo_form_trigger\" style=\"text-decoration: underline\">Haven't signed up for texts yet? Sign up &amp; get your free code here.<\/a><\/div>\n<script type=\"text\/javascript\">\n\tdocument.querySelector('.klaviyo_form_trigger').addEventListener('click', function (){\n\t\twindow._klOnsite = window._klOnsite || [];\nwindow._klOnsite.push(['openForm', 'TwYkgx']);\n\t});\n<\/script>","background_type":"full_width","background":"rgba(0,0,0,0)","text_color":"rgba(0,0,0,0)"}},"16552124559d3d5239":{"type":"custom-html","disabled":true,"settings":{"subheading":"","title":"","html":"<p style=\"text-align: center\">Grab a discount code when you sign up for ELEDLights texts, and use it to save on our best in-stock LED lighting fixtures and retrofits.<\/p>","background_type":"full_width","background":"rgba(0,0,0,0)","text_color":"rgba(0,0,0,0)"}},"1655212330fa9b7e23":{"type":"custom-html","settings":{"subheading":"","title":"","html":"<hr>","background_type":"full_width","background":"rgba(0,0,0,0)","text_color":"rgba(0,0,0,0)"}},"1655211846020e5d22":{"type":"collection-list","blocks":{"1655211846d1d143bf-0":{"type":"collection","settings":{"collection":"led-tube-lights","subheading":"","title":"LED Tubes","link_text":"","link_url":"","text_color":"#2e2e2e","overlay_color":"#000000","overlay_opacity":0}},"1655211846d1d143bf-1":{"type":"collection","settings":{"collection":"led-high-bays","subheading":"","title":"High Bay Lights","link_text":"","link_url":"","text_color":"#2e2e2e","overlay_color":"#000000","overlay_opacity":0}},"1655211846d1d143bf-2":{"type":"collection","settings":{"collection":"flood-lights","subheading":"","title":"Flood Lights","link_text":"","link_url":"","text_color":"#2e2e2e","overlay_color":"#000000","overlay_opacity":0}},"1655211846d1d143bf-3":{"type":"collection","settings":{"collection":"led-strips","subheading":"","title":"LED Strip Retrofit Kits","link_text":"","link_url":"","text_color":"#2e2e2e","overlay_color":"#000000","overlay_opacity":0}},"1655211846d1d143bf-4":{"type":"collection","settings":{"collection":"shoebox-area-lights-old-afbb68","subheading":"","title":"Shoebox Area Lights","link_text":"","link_url":"","text_color":"#2e2e2e","overlay_color":"#000000","overlay_opacity":0}},"1655211846d1d143bf-5":{"type":"collection","settings":{"collection":"indoor-screw-in-retrofits","subheading":"","title":"Screw-in LED Retrofits","link_text":"","link_url":"","text_color":"#2e2e2e","overlay_color":"#000000","overlay_opacity":0}}},"block_order":["1655211846d1d143bf-0","1655211846d1d143bf-1","1655211846d1d143bf-2","1655211846d1d143bf-3","1655211846d1d143bf-4","1655211846d1d143bf-5"],"settings":{"reveal_on_scroll":false,"layout":"grid","subheading":"","title":"Shop By Light Type","background":"rgba(0,0,0,0)","text_color":"rgba(0,0,0,0)"}},"1655212354c2f6c2fa":{"type":"custom-html","settings":{"subheading":"","title":"","html":"<div style=\"text-align: center\"><a style=\"text-decoration: underline; font-size: 18px;\" href=\"https:\/\/www.eledlights.com\/pages\/led-lights\">See All Lighting Categories<\/a><\/div>","background_type":"boxed","background":"rgba(0,0,0,0)","text_color":"rgba(0,0,0,0)"}},"1655212325d51ce2ea":{"type":"custom-html","settings":{"subheading":"","title":"","html":"<hr>","background_type":"boxed","background":"rgba(0,0,0,0)","text_color":"rgba(0,0,0,0)"}},"16552122213a78076a":{"type":"rich-text","settings":{"subheading":"Get Great Lights Fast","title":"Bestsellers in LED Lighting","content":"<p>Shop our top-selling ready-to-ship LED lights and have great lighting ready to install in no time.<\/p>","button_text":"","button_link":"","background_type":"full_width","text_width":"large","text_position":"center","text_alignment":"center","background":"rgba(0,0,0,0)","heading_color":"rgba(0,0,0,0)","text_color":"rgba(0,0,0,0)","button_background":"rgba(0,0,0,0)","button_text_color":"rgba(0,0,0,0)"}},"main":{"type":"main-collection","settings":{"top_of_page":false,"show_sort_by":true,"products_per_page":15,"mobile_products_per_row":"2","desktop_products_per_row":5,"show_filters":false,"show_filter_group_name":false,"show_color_swatch":true,"open_first_filter_group":false,"filter_position":"drawer","promotion_position":"top","promotion_height":"small"}},"1647959183c614db7d":{"type":"recently-viewed-products","settings":{"subheading":"","title":"Recently Viewed","products_count":6,"background":"#f5f5f5","text_color":"rgba(0,0,0,0)"}}},"order":["collection-banner","1655212869259e08a7","165540493133ea9de2","16552124559d3d5239","1655212330fa9b7e23","1655211846020e5d22","1655212354c2f6c2fa","1655212325d51ce2ea","16552122213a78076a","main","1647959183c614db7d"]}