{"sections":{"main":{"type":"main-page","settings":{"show_title":true,"page_width":"large"}},"1e251f8f-f5e7-40c8-a54a-e4dbcbd0374d":{"type":"custom-html","settings":{"subheading":"","title":"","html":"<p style=\"max-width: 1200px; margin: 0 auto;\">In addition to what you find on our website, ELEDLights represents a large collection of quality lighting brands. By creating solid partnerships, we have access to a wealth of products, from lights and fixtures to poles and smart controls—we can help get you anything you need for your project. If there is a brand or product you are specifically looking for, feel free to reach out to our sales team by filling out the form below.<\/p>","background_type":"full_width","background":"rgba(0,0,0,0)","text_color":"rgba(0,0,0,0)"}},"1647875822954a5b1f":{"type":"custom-html","settings":{"subheading":"","title":"Lighting Brands We Work With","html":"<style>\n  .manufacturer-grid {\n    display: flex;\n    align-items: center;\n    justify-content: center;\n    flex-wrap: wrap;\n    max-width: 1300px;\n    margin: 0 auto;\n  }\n\n  .manufacturer-grid img {\n    width: 222px;\n    padding-right: 45px;\n    padding-left: 45px;\n    margin-top: 21px !important;\n    margin-bottom: 21px !important;\n  }\n<\/style>\n\n<div class=\"manufacturer-grid\">\n  <a href=\"https:\/\/www.alconlighting.com\" target=\"_blank\"><img src=\"https:\/\/cdn.shopify.com\/s\/files\/1\/0553\/0605\/9812\/files\/Alcon_Lighting.png?v=1678216669\" alt=\"Alcon Lighting\" loading=\"lazy\"><\/a>\n<a href=\"https:\/\/www.archipelagolighting.com\" target=\"_blank\"><img src=\"https:\/\/cdn.shopify.com\/s\/files\/1\/0553\/0605\/9812\/files\/archipelago.png?v=1697053884\"><\/a>\n  <a href=\"https:\/\/falconlights.pk\" target=\"_blank\"><img src=\"https:\/\/cdn.shopify.com\/s\/files\/1\/0553\/0605\/9812\/files\/Falcon_LED_Lights.jpg?v=1678216670\" alt=\"Falcon LED Lights\" loading=\"lazy\">\n  <\/a><a href=\"https:\/\/www.feit.com\/\" target=\"_blank\"><img src=\"https:\/\/cdn.shopify.com\/s\/files\/1\/0553\/0605\/9812\/files\/Feit_Electric.png?v=1678216670\" alt=\"Feit Electric\" loading=\"lazy\">\n  <\/a><a href=\"https:\/\/www.filamento.com\" target=\"_blank\"><img src=\"https:\/\/cdn.shopify.com\/s\/files\/1\/0553\/0605\/9812\/files\/filamento.jpg?v=1678216670\" alt=\"Filamento\" loading=\"lazy\">\n  <\/a><a href=\"https:\/\/www.flexfireleds.com\" target=\"_blank\"><img src=\"https:\/\/cdn.shopify.com\/s\/files\/1\/0553\/0605\/9812\/files\/Flexfire_LEDs.jpg?v=1678216670\" alt=\"Flexfire LEDs\" loading=\"lazy\">\n  <\/a><a href=\"https:\/\/www.gecurrent.com\" target=\"_blank\"><img src=\"https:\/\/cdn.shopify.com\/s\/files\/1\/0553\/0605\/9812\/files\/GE_Current.jpg?v=1678216670\" alt=\"GE Current\" loading=\"lazy\">\n  <\/a><a href=\"https:\/\/www.gecurrent.com\/inspiration\/acquisition-of-hubbell-commercial-industrial-lighting-business-complete\" target=\"_blank\"><img src=\"https:\/\/cdn.shopify.com\/s\/files\/1\/0553\/0605\/9812\/files\/Hubbell_Lighting.png?v=1678216670\" alt=\"Hubbell Lighting\" loading=\"lazy\">\n  <\/a><a href=\"https:\/\/www.hapco.com\" target=\"_blank\"><img src=\"https:\/\/cdn.shopify.com\/s\/files\/1\/0553\/0605\/9812\/files\/Hapco.jpg?v=1678216670\" alt=\"Hapco Pole Products\" loading=\"lazy\">\n  <\/a><a href=\"https:\/\/www.intermatic.com\/\" target=\"_blank\"><img src=\"https:\/\/cdn.shopify.com\/s\/files\/1\/0553\/0605\/9812\/files\/Intermatic.jpg?v=1678216670\" alt=\"Intermatic\" loading=\"lazy\">\n  <\/a><a href=\"https:\/\/www.kelvix.com\" target=\"_blank\"><img src=\"https:\/\/cdn.shopify.com\/s\/files\/1\/0553\/0605\/9812\/files\/Kelvix_Lighting.jpg?v=1678216670\" alt=\"Kelvix Lighting\" loading=\"lazy\">\n  <\/a><a href=\"https:\/\/keystonetech.com\" target=\"_blank\"><img src=\"https:\/\/cdn.shopify.com\/s\/files\/1\/0553\/0605\/9812\/files\/Keystone.jpg?v=1678216670\" alt=\"Keystone\" loading=\"lazy\">\n  <\/a><a href=\"https:\/\/www.ledlivingtechnology.com\" target=\"_blank\"><img src=\"https:\/\/cdn.shopify.com\/s\/files\/1\/0553\/0605\/9812\/files\/led-living.png?v=1678217840\" alt=\"LED Living\" loading=\"lazy\">\n  <\/a><a href=\"https:\/\/www.leviton.com\/en\" target=\"_blank\"><img src=\"https:\/\/cdn.shopify.com\/s\/files\/1\/0553\/0605\/9812\/files\/Leviton.jpg?v=1678216670\" alt=\"Leviton\" loading=\"lazy\">\n  <\/a><a href=\"https:\/\/www.lifx.com\" target=\"_blank\"><img src=\"https:\/\/cdn.shopify.com\/s\/files\/1\/0553\/0605\/9812\/files\/LIFX.jpg?v=1678216670\" alt=\"LIFX\" loading=\"lazy\">\n  <\/a><a href=\"https:\/\/www.led-llc.com\" target=\"_blank\"><img src=\"https:\/\/cdn.shopify.com\/s\/files\/1\/0553\/0605\/9812\/files\/Light_Efficient_Design.jpg?v=1678216670\" alt=\"Light Efficient Design\" loading=\"lazy\">\n  <\/a><a href=\"https:\/\/lightheadedlighting.com\" target=\"_blank\"><img src=\"https:\/\/cdn.shopify.com\/s\/files\/1\/0553\/0605\/9812\/files\/Lightheaded.png?v=1678216670\" alt=\"Lightheaded Lighting\" loading=\"lazy\">\n  <\/a><a href=\"https:\/\/lithonia.acuitybrands.com\" target=\"_blank\"><img src=\"https:\/\/cdn.shopify.com\/s\/files\/1\/0553\/0605\/9812\/files\/lithonia-lighting.png?v=1699024063\" alt=\"Lithonia Lighting\" loading=\"lazy\">\n  <\/a><a href=\"https:\/\/liton.com\" target=\"_blank\"><img src=\"https:\/\/cdn.shopify.com\/s\/files\/1\/0553\/0605\/9812\/files\/Liton.gif?v=1678216670\" alt=\"Liton\" loading=\"lazy\">\n  <\/a><a href=\"https:\/\/lumetta.com\" target=\"_blank\"><img src=\"https:\/\/cdn.shopify.com\/s\/files\/1\/0553\/0605\/9812\/files\/Lumetta.jpg?v=1678216670\" alt=\"Lumetta\" loading=\"lazy\">\n  <\/a><a href=\"https:\/\/www.luminii.com\" target=\"_blank\"><img src=\"https:\/\/cdn.shopify.com\/s\/files\/1\/0553\/0605\/9812\/files\/LUMINII.jpg?v=1678216670\" alt=\"LUMINII\" loading=\"lazy\">\n  <\/a><a href=\"https:\/\/www.maxlite.com\" target=\"_blank\"><img src=\"https:\/\/cdn.shopify.com\/s\/files\/1\/0553\/0605\/9812\/files\/Maxlite.png?v=1678216670\" alt=\"MaxLite\" loading=\"lazy\">\n  <\/a><a href=\"https:\/\/noralighting.com\" target=\"_blank\"><img src=\"https:\/\/cdn.shopify.com\/s\/files\/1\/0553\/0605\/9812\/files\/Nora_Lighting.jpg?v=1678216670\" alt=\"Nora Lighting\" loading=\"lazy\">\n  <\/a><a href=\"https:\/\/www.orionlighting.com\" target=\"_blank\"><img src=\"https:\/\/cdn.shopify.com\/s\/files\/1\/0553\/0605\/9812\/files\/Orion.jpg?v=1678216670\" alt=\"Orion Energy Systems\" loading=\"lazy\">\n  <\/a><a href=\"https:\/\/www.rablighting.com\" target=\"_blank\"><img src=\"https:\/\/cdn.shopify.com\/s\/files\/1\/0553\/0605\/9812\/files\/RAB.png?v=1697053137\" alt=\"RAB Lighting\" loading=\"lazy\">\n  <\/a><a href=\"https:\/\/www.studiomlighting.com\" target=\"_blank\"><img src=\"https:\/\/cdn.shopify.com\/s\/files\/1\/0553\/0605\/9812\/files\/Studio_M_Lighting.jpg?v=1678216670\" alt=\"Studio M\" loading=\"lazy\">\n  <\/a><a href=\"https:\/\/www.waclighting.com\" target=\"_blank\"><img src=\"https:\/\/cdn.shopify.com\/s\/files\/1\/0553\/0605\/9812\/files\/WAC_Lighting.jpg?v=1678216670\" alt=\"WAC Lighting\" loading=\"lazy\">\n\n<\/a>\n<\/div><a href=\"https:\/\/www.waclighting.com\" target=\"_blank\">\n<\/a><a name=\"contact-form\"><\/a>","background_type":"full_width","background":"rgba(0,0,0,0)","text_color":"rgba(0,0,0,0)"}},"4163e7ba-dd19-4c4d-a931-f5f5b86d07c8":{"type":"custom-html","settings":{"subheading":"","title":"","html":"{formbuilder:MTA4NzQ4}","background_type":"full_width","background":"rgba(0,0,0,0)","text_color":"rgba(0,0,0,0)"}}},"order":["main","1e251f8f-f5e7-40c8-a54a-e4dbcbd0374d","1647875822954a5b1f","4163e7ba-dd19-4c4d-a931-f5f5b86d07c8"]}